scratch.py
semantic_retrieval/__init__.py
semantic_retrieval/access_control/__init__.py
semantic_retrieval/access_control/access_function.py
semantic_retrieval/access_control/access_identity.py
semantic_retrieval/access_control/access_passport.py
semantic_retrieval/access_control/always_allow_document_access_policy_factory.py
semantic_retrieval/access_control/document_access_policy_factory.py
semantic_retrieval/access_control/resource_access_policy.py
semantic_retrieval/access_control/policies/__init__.py
semantic_retrieval/access_control/policies/always_allow_access_policy.py
semantic_retrieval/common/__init__.py
semantic_retrieval/common/base.py
semantic_retrieval/common/core.py
semantic_retrieval/common/json_types.py
semantic_retrieval/common/storage.py
semantic_retrieval/common/types.py
semantic_retrieval/data_store/__init__.py
semantic_retrieval/data_store/vector_dbs/__init__.py
semantic_retrieval/data_store/vector_dbs/pinecone_vector_db.py
semantic_retrieval/data_store/vector_dbs/vector_db.py
semantic_retrieval/document/__init__.py
semantic_retrieval/document/document.py
semantic_retrieval/document/metadata/__init__.py
semantic_retrieval/document/metadata/document_metadata.py
semantic_retrieval/document/metadata/document_metadata_db.py
semantic_retrieval/document/metadata/in_memory_document_metadata_db.py
semantic_retrieval/document_parsers/__init__.py
semantic_retrieval/document_parsers/direct_document_parser.py
semantic_retrieval/document_parsers/multi_document_parser.py
semantic_retrieval/document_parsers/parser_registry.py
semantic_retrieval/evaluation/__init__.py
semantic_retrieval/evaluation/lib.py
semantic_retrieval/evaluation/metrics.py
semantic_retrieval/functional/functional.py
semantic_retrieval/generator/__init__.py
semantic_retrieval/generator/completion_generator.py
semantic_retrieval/generator/completion_models/__init__.py
semantic_retrieval/generator/completion_models/completion_model.py
python_semantic_retrieval-0.1.3.dist-info/METADATA
python_semantic_retrieval-0.1.3.dist-info/WHEEL
python_semantic_retrieval-0.1.3.dist-info/top_level.txt
python_semantic_retrieval-0.1.3.dist-info/RECORD
